bootstrapper/__init__.py
bootstrapper/cli.py
project_bootstrapper-0.1.1.dist-info/METADATA
project_bootstrapper-0.1.1.dist-info/WHEEL
project_bootstrapper-0.1.1.dist-info/entry_points.txt
project_bootstrapper-0.1.1.dist-info/top_level.txt
project_bootstrapper-0.1.1.dist-info/RECORD
