Metadata-Version: 2.4
Name: project-bootstrapper
Version: 0.1.1
Summary: A CLI tool to bootstrap Python projects with Git and venv support.
Home-page: https://github.com/Danny26y/python-cli-bootstrapper
Author: Yeke Daniel
Author-email: Danielyeke489@gmail.com
Classifier: Programming Language :: Python :: 3
Classifier: License :: OSI Approved :: MIT License
Classifier: Operating System :: OS Independent
Requires-Python: >=3.6
Dynamic: author
Dynamic: author-email
Dynamic: classifier
Dynamic: description
Dynamic: description-content-type
Dynamic: home-page
Dynamic: requires-python
Dynamic: summary
